pycurrencychecker/__init__.py
pycurrencychecker/pycurrencychecker.py
pycurrencychecker/utils/__init__.py
pycurrencychecker/utils/urls.py
pycurrencychecker-1.0.1.dist-info/LICENSE
pycurrencychecker-1.0.1.dist-info/METADATA
pycurrencychecker-1.0.1.dist-info/WHEEL
pycurrencychecker-1.0.1.dist-info/RECORD
