Metadata-Version: 2.3
Name: pycurrencychecker
Version: 1.0.1
Summary: A simple and easy-to-use Python library for retrieving current currency exchange rates.
License: MIT
Keywords: currency,exchange rates,forex,finance
Author: GuillerCH
Author-email: guillerc33@gmail.com
Requires-Python: >=3.8
Classifier: License :: OSI Approved :: MIT License
Classifier: Programming Language :: Python :: 3
Classifier: Programming Language :: Python :: 3.8
Classifier: Programming Language :: Python :: 3.9
Classifier: Programming Language :: Python :: 3.10
Classifier: Programming Language :: Python :: 3.11
Classifier: Programming Language :: Python :: 3.12
Classifier: Programming Language :: Python :: 3.13
Requires-Dist: requests (>=2.0,<3.0)
Project-URL: Homepage, https://github.com/gcordovadatec/pycurrencychecker
Project-URL: Repository, https://github.com/gcordovadatec/pycurrencychecker
